{
  "actions" : [ {
    "module" : "init",
    "date" : "2023-12-07T16:42:54.191874496Z",
    "properties" : {
      "projectName" : "JHipster Lite Sample Application",
      "baseName" : "litesample",
      "packageName" : "tech.jhipster.lite.sample"
    }
  }, {
    "module" : "maven-java",
    "date" : "2023-12-07T16:42:54.341943160Z",
    "properties" : {
      "projectName" : "JHipster Lite Sample Application",
      "baseName" : "litesample",
      "packageName" : "tech.jhipster.lite.sample"
    }
  }, {
    "module" : "java-base",
    "date" : "2023-12-07T16:42:54.373737817Z",
    "properties" : {
      "projectName" : "JHipster Lite Sample Application",
      "baseName" : "litesample",
      "packageName" : "tech.jhipster.lite.sample"
    }
  }, {
    "module" : "jacoco-check-min-coverage",
    "date" : "2023-12-07T16:42:54.384432804Z",
    "properties" : {
      "projectName" : "JHipster Lite Sample Application",
      "baseName" : "litesample",
      "packageName" : "tech.jhipster.lite.sample"
    }
  }, {
    "module" : "java-memoizers",
    "date" : "2023-12-07T16:42:54.394734910Z",
    "properties" : {
      "projectName" : "JHipster Lite Sample Application",
      "baseName" : "litesample",
      "packageName" : "tech.jhipster.lite.sample"
    }
  }, {
    "module" : "java-enums",
    "date" : "2023-12-07T16:42:54.404843627Z",
    "properties" : {
      "projectName" : "JHipster Lite Sample Application",
      "baseName" : "litesample",
      "packageName" : "tech.jhipster.lite.sample"
    }
  }, {
    "module" : "pagination-domain",
    "date" : "2023-12-07T16:42:54.424643515Z",
    "properties" : {
      "projectName" : "JHipster Lite Sample Application",
      "baseName" : "litesample",
      "packageName" : "tech.jhipster.lite.sample"
    }
  }, {
    "module" : "application-service-hexagonal-architecture-documentation",
    "date" : "2023-12-07T16:42:54.434786168Z",
    "properties" : {
      "projectName" : "JHipster Lite Sample Application",
      "baseName" : "litesample",
      "packageName" : "tech.jhipster.lite.sample"
    }
  }, {
    "module" : "spring-boot",
    "date" : "2023-12-07T16:42:54.485108085Z",
    "properties" : {
      "projectName" : "JHipster Lite Sample Application",
      "baseName" : "litesample",
      "packageName" : "tech.jhipster.lite.sample"
    }
  }, {
    "module" : "logs-spy",
    "date" : "2023-12-07T16:42:54.496047121Z",
    "properties" : {
      "projectName" : "JHipster Lite Sample Application",
      "baseName" : "litesample",
      "packageName" : "tech.jhipster.lite.sample"
    }
  }, {
    "module" : "spring-boot-mvc-empty",
    "date" : "2023-12-07T16:42:54.505548410Z",
    "properties" : {
      "projectName" : "JHipster Lite Sample Application",
      "baseName" : "litesample",
      "packageName" : "tech.jhipster.lite.sample"
    }
  }, {
    "module" : "spring-boot-tomcat",
    "date" : "2023-12-07T16:42:54.531295754Z",
    "properties" : {
      "projectName" : "JHipster Lite Sample Application",
      "baseName" : "litesample",
      "packageName" : "tech.jhipster.lite.sample"
    }
  }, {
    "module" : "spring-boot-actuator",
    "date" : "2023-12-07T16:42:54.552051672Z",
    "properties" : {
      "projectName" : "JHipster Lite Sample Application",
      "baseName" : "litesample",
      "packageName" : "tech.jhipster.lite.sample"
    }
  }, {
    "module" : "spring-boot-async",
    "date" : "2023-12-07T16:42:54.567518961Z",
    "properties" : {
      "projectName" : "JHipster Lite Sample Application",
      "baseName" : "litesample",
      "packageName" : "tech.jhipster.lite.sample"
    }
  }, {
    "module" : "spring-boot-devtools",
    "date" : "2023-12-07T16:42:54.584066656Z",
    "properties" : {
      "projectName" : "JHipster Lite Sample Application",
      "baseName" : "litesample",
      "packageName" : "tech.jhipster.lite.sample"
    }
  }, {
    "module" : "java-archunit",
    "date" : "2023-12-07T16:42:54.599279966Z",
    "properties" : {
      "projectName" : "JHipster Lite Sample Application",
      "baseName" : "litesample",
      "packageName" : "tech.jhipster.lite.sample"
    }
  }, {
    "module" : "git-information",
    "date" : "2023-12-07T16:42:54.621486030Z",
    "properties" : {
      "projectName" : "JHipster Lite Sample Application",
      "baseName" : "litesample",
      "packageName" : "tech.jhipster.lite.sample"
    }
  }, {
    "module" : "prettier",
    "date" : "2023-12-07T16:42:54.637544486Z",
    "properties" : {
      "projectName" : "JHipster Lite Sample Application",
      "baseName" : "litesample",
      "packageName" : "tech.jhipster.lite.sample"
    }
  }, {
    "module" : "frontend-maven-plugin",
    "date" : "2023-12-07T16:42:54.681340782Z",
    "properties" : {
      "projectName" : "JHipster Lite Sample Application",
      "baseName" : "litesample",
      "packageName" : "tech.jhipster.lite.sample"
    }
  }, {
    "module" : "vue-core",
    "date" : "2023-12-07T16:42:54.709512285Z",
    "properties" : {
      "projectName" : "JHipster Lite Sample Application",
      "baseName" : "litesample",
      "packageName" : "tech.jhipster.lite.sample"
    }
  }, {
    "module" : "sonar-qube-java-backend-and-frontend",
    "date" : "2023-12-07T16:42:54.731027967Z",
    "properties" : {
      "projectName" : "JHipster Lite Sample Application",
      "baseName" : "litesample",
      "packageName" : "tech.jhipster.lite.sample"
    }
  }, {
    "module" : "postgresql",
    "date" : "2023-12-07T16:42:54.781905665Z",
    "properties" : {
      "projectName" : "JHipster Lite Sample Application",
      "baseName" : "litesample",
      "packageName" : "tech.jhipster.lite.sample"
    }
  }, {
    "module" : "liquibase",
    "date" : "2023-12-07T16:42:54.803855323Z",
    "properties" : {
      "projectName" : "JHipster Lite Sample Application",
      "baseName" : "litesample",
      "packageName" : "tech.jhipster.lite.sample"
    }
  }, {
    "module" : "spring-boot-oauth2",
    "date" : "2023-12-07T16:42:54.839116731Z",
    "properties" : {
      "projectName" : "JHipster Lite Sample Application",
      "baseName" : "litesample",
      "packageName" : "tech.jhipster.lite.sample"
    }
  }, {
    "module" : "spring-boot-oauth2-account",
    "date" : "2023-12-07T16:42:54.853500517Z",
    "properties" : {
      "projectName" : "JHipster Lite Sample Application",
      "baseName" : "litesample",
      "packageName" : "tech.jhipster.lite.sample"
    }
  }, {
    "module" : "springdoc-mvc-openapi",
    "date" : "2023-12-07T16:42:54.878794810Z",
    "properties" : {
      "projectName" : "JHipster Lite Sample Application",
      "baseName" : "litesample",
      "packageName" : "tech.jhipster.lite.sample"
    }
  }, {
    "module" : "springdoc-oauth2",
    "date" : "2023-12-07T16:42:54.892570328Z",
    "properties" : {
      "projectName" : "JHipster Lite Sample Application",
      "baseName" : "litesample",
      "packageName" : "tech.jhipster.lite.sample"
    }
  }, {
    "module" : "spring-boot-cucumber-mvc",
    "date" : "2023-12-07T16:42:54.921308045Z",
    "properties" : {
      "projectName" : "JHipster Lite Sample Application",
      "baseName" : "litesample",
      "packageName" : "tech.jhipster.lite.sample"
    }
  }, {
    "module" : "spring-boot-cucumber-oauth2-authentication",
    "date" : "2023-12-07T16:42:54.948727035Z",
    "properties" : {
      "projectName" : "JHipster Lite Sample Application",
      "baseName" : "litesample",
      "packageName" : "tech.jhipster.lite.sample"
    }
  }, {
    "module" : "kipe-expression",
    "date" : "2023-12-07T16:42:54.961404857Z",
    "properties" : {
      "projectName" : "JHipster Lite Sample Application",
      "baseName" : "litesample",
      "packageName" : "tech.jhipster.lite.sample"
    }
  }, {
    "module" : "kipe-authorization",
    "date" : "2023-12-07T16:42:54.972581163Z",
    "properties" : {
      "projectName" : "JHipster Lite Sample Application",
      "baseName" : "litesample",
      "packageName" : "tech.jhipster.lite.sample"
    }
  }, {
    "module" : "dummy-feature",
    "date" : "2023-12-07T16:42:54.986745847Z",
    "properties" : {
      "projectName" : "JHipster Lite Sample Application",
      "baseName" : "litesample",
      "packageName" : "tech.jhipster.lite.sample"
    }
  } ]
}