{
  "actions": [
    {
      "module": "init",
      "date": "2025-01-31T19:47:37.016044287Z",
      "properties": {
        "projectName": "JHipster Lite Sample Application",
        "baseName": "litesample",
        "packageName": "tech.jhipster.lite.sample"
      }
    },
    {
      "module": "maven-java",
      "date": "2025-01-31T19:47:37.053696563Z",
      "properties": {
        "projectName": "JHipster Lite Sample Application",
        "baseName": "litesample",
        "packageName": "tech.jhipster.lite.sample"
      }
    },
    {
      "module": "maven-wrapper",
      "date": "2025-01-31T19:47:37.073108256Z",
      "properties": {
        "projectName": "JHipster Lite Sample Application",
        "baseName": "litesample",
        "packageName": "tech.jhipster.lite.sample"
      }
    },
    {
      "module": "java-base",
      "date": "2025-01-31T19:47:37.130185694Z",
      "properties": {
        "projectName": "JHipster Lite Sample Application",
        "baseName": "litesample",
        "packageName": "tech.jhipster.lite.sample"
      }
    },
    {
      "module": "jacoco-with-min-coverage-check",
      "date": "2025-01-31T19:47:37.173708492Z",
      "properties": {
        "projectName": "JHipster Lite Sample Application",
        "baseName": "litesample",
        "packageName": "tech.jhipster.lite.sample"
      }
    },
    {
      "module": "java-memoizers",
      "date": "2025-01-31T19:47:37.208851750Z",
      "properties": {
        "projectName": "JHipster Lite Sample Application",
        "baseName": "litesample",
        "packageName": "tech.jhipster.lite.sample"
      }
    },
    {
      "module": "java-enums",
      "date": "2025-01-31T19:47:37.241220238Z",
      "properties": {
        "projectName": "JHipster Lite Sample Application",
        "baseName": "litesample",
        "packageName": "tech.jhipster.lite.sample"
      }
    },
    {
      "module": "pagination-domain",
      "date": "2025-01-31T19:47:37.302927372Z",
      "properties": {
        "projectName": "JHipster Lite Sample Application",
        "baseName": "litesample",
        "packageName": "tech.jhipster.lite.sample"
      }
    },
    {
      "module": "application-service-hexagonal-architecture-documentation",
      "date": "2025-01-31T19:47:37.378228570Z",
      "properties": {
        "projectName": "JHipster Lite Sample Application",
        "baseName": "litesample",
        "packageName": "tech.jhipster.lite.sample"
      }
    },
    {
      "module": "spring-boot",
      "date": "2025-01-31T19:47:37.514514533Z",
      "properties": {
        "projectName": "JHipster Lite Sample Application",
        "baseName": "litesample",
        "packageName": "tech.jhipster.lite.sample"
      }
    },
    {
      "module": "logs-spy",
      "date": "2025-01-31T19:47:37.596687621Z",
      "properties": {
        "projectName": "JHipster Lite Sample Application",
        "baseName": "litesample",
        "packageName": "tech.jhipster.lite.sample"
      }
    },
    {
      "module": "spring-boot-mvc-empty",
      "date": "2025-01-31T19:47:37.631034713Z",
      "properties": {
        "projectName": "JHipster Lite Sample Application",
        "baseName": "litesample",
        "packageName": "tech.jhipster.lite.sample"
      }
    },
    {
      "module": "spring-boot-tomcat",
      "date": "2025-01-31T19:47:37.725863989Z",
      "properties": {
        "projectName": "JHipster Lite Sample Application",
        "baseName": "litesample",
        "packageName": "tech.jhipster.lite.sample"
      }
    },
    {
      "module": "spring-boot-actuator",
      "date": "2025-01-31T19:47:37.812310255Z",
      "properties": {
        "projectName": "JHipster Lite Sample Application",
        "baseName": "litesample",
        "packageName": "tech.jhipster.lite.sample"
      }
    },
    {
      "module": "spring-boot-async",
      "date": "2025-01-31T19:47:37.861648999Z",
      "properties": {
        "projectName": "JHipster Lite Sample Application",
        "baseName": "litesample",
        "packageName": "tech.jhipster.lite.sample"
      }
    },
    {
      "module": "spring-boot-devtools",
      "date": "2025-01-31T19:47:37.927184045Z",
      "properties": {
        "projectName": "JHipster Lite Sample Application",
        "baseName": "litesample",
        "packageName": "tech.jhipster.lite.sample"
      }
    },
    {
      "module": "java-archunit",
      "date": "2025-01-31T19:47:38.017411883Z",
      "properties": {
        "projectName": "JHipster Lite Sample Application",
        "baseName": "litesample",
        "packageName": "tech.jhipster.lite.sample"
      }
    },
    {
      "module": "git-information",
      "date": "2025-01-31T19:47:38.132580991Z",
      "properties": {
        "projectName": "JHipster Lite Sample Application",
        "baseName": "litesample",
        "packageName": "tech.jhipster.lite.sample"
      }
    },
    {
      "module": "prettier",
      "date": "2025-01-31T19:47:38.202002536Z",
      "properties": {
        "projectName": "JHipster Lite Sample Application",
        "baseName": "litesample",
        "packageName": "tech.jhipster.lite.sample"
      }
    },
    {
      "module": "typescript",
      "date": "2025-01-31T19:47:38.308497428Z",
      "properties": {
        "projectName": "JHipster Lite Sample Application",
        "baseName": "litesample",
        "packageName": "tech.jhipster.lite.sample"
      }
    },
    {
      "module": "frontend-maven-plugin",
      "date": "2025-01-31T19:47:38.445217496Z",
      "properties": {
        "projectName": "JHipster Lite Sample Application",
        "baseName": "litesample",
        "packageName": "tech.jhipster.lite.sample"
      }
    },
    {
      "module": "vue-core",
      "date": "2025-01-31T19:47:38.596546008Z",
      "properties": {
        "projectName": "JHipster Lite Sample Application",
        "baseName": "litesample",
        "packageName": "tech.jhipster.lite.sample"
      }
    },
    {
      "module": "sonar-qube-java-backend-and-frontend",
      "date": "2025-01-31T19:47:38.726971219Z",
      "properties": {
        "projectName": "JHipster Lite Sample Application",
        "baseName": "litesample",
        "packageName": "tech.jhipster.lite.sample"
      }
    },
    {
      "module": "datasource-postgresql",
      "date": "2025-01-31T19:47:38.942687171Z",
      "properties": {
        "projectName": "JHipster Lite Sample Application",
        "baseName": "litesample",
        "packageName": "tech.jhipster.lite.sample"
      }
    },
    {
      "module": "jpa-postgresql",
      "date": "2025-01-31T19:47:39.099745058Z",
      "properties": {
        "projectName": "JHipster Lite Sample Application",
        "baseName": "litesample",
        "packageName": "tech.jhipster.lite.sample"
      }
    },
    {
      "module": "liquibase",
      "date": "2025-01-31T19:47:39.193580512Z",
      "properties": {
        "projectName": "JHipster Lite Sample Application",
        "baseName": "litesample",
        "packageName": "tech.jhipster.lite.sample"
      }
    },
    {
      "module": "spring-boot-oauth2",
      "date": "2025-01-31T19:47:39.438537910Z",
      "properties": {
        "projectName": "JHipster Lite Sample Application",
        "baseName": "litesample",
        "packageName": "tech.jhipster.lite.sample"
      }
    },
    {
      "module": "spring-boot-oauth2-account",
      "date": "2025-01-31T19:47:39.519825640Z",
      "properties": {
        "projectName": "JHipster Lite Sample Application",
        "baseName": "litesample",
        "packageName": "tech.jhipster.lite.sample"
      }
    },
    {
      "module": "springdoc-mvc-openapi",
      "date": "2025-01-31T19:47:39.677580997Z",
      "properties": {
        "projectName": "JHipster Lite Sample Application",
        "baseName": "litesample",
        "packageName": "tech.jhipster.lite.sample"
      }
    },
    {
      "module": "springdoc-oauth2",
      "date": "2025-01-31T19:47:39.775909918Z",
      "properties": {
        "projectName": "JHipster Lite Sample Application",
        "baseName": "litesample",
        "packageName": "tech.jhipster.lite.sample"
      }
    },
    {
      "module": "spring-boot-cucumber-mvc",
      "date": "2025-01-31T19:47:39.913034449Z",
      "properties": {
        "projectName": "JHipster Lite Sample Application",
        "baseName": "litesample",
        "packageName": "tech.jhipster.lite.sample"
      }
    },
    {
      "module": "spring-boot-cucumber-oauth2-authentication",
      "date": "2025-01-31T19:47:40.057945189Z",
      "properties": {
        "projectName": "JHipster Lite Sample Application",
        "baseName": "litesample",
        "packageName": "tech.jhipster.lite.sample"
      }
    },
    {
      "module": "kipe-expression",
      "date": "2025-01-31T19:47:40.148948173Z",
      "properties": {
        "projectName": "JHipster Lite Sample Application",
        "baseName": "litesample",
        "packageName": "tech.jhipster.lite.sample"
      }
    },
    {
      "module": "kipe-authorization",
      "date": "2025-01-31T19:47:40.241586249Z",
      "properties": {
        "projectName": "JHipster Lite Sample Application",
        "baseName": "litesample",
        "packageName": "tech.jhipster.lite.sample"
      }
    },
    {
      "module": "sample-feature",
      "date": "2025-01-31T19:47:40.372569347Z",
      "properties": {
        "projectName": "JHipster Lite Sample Application",
        "baseName": "litesample",
        "packageName": "tech.jhipster.lite.sample"
      }
    }
  ]
}
